py_package_updater/__init__.py
py_package_updater/__main__.py
py_package_updater/environment_manager.py
py_package_updater/file_updater.py
py_package_updater/package_manager.py
py_package_updater/test_discovery.py
py_package_updater/update_tester.py
py_package_updater-0.1.3.dist-info/licenses/LICENSE
py_package_updater-0.1.3.dist-info/METADATA
py_package_updater-0.1.3.dist-info/WHEEL
py_package_updater-0.1.3.dist-info/entry_points.txt
py_package_updater-0.1.3.dist-info/top_level.txt
py_package_updater-0.1.3.dist-info/RECORD
