Metadata-Version: 2.4
Name: py_package_updater
Version: 0.1.3
Summary: A smart Python package updater that safely upgrades dependencies while verifying tests pass.
Author-email: Harmanpreet Bhatti <data2k18@gmail.com>
License-Expression: MIT
Keywords: package-manager,dependency-management,testing,automation,requirements,pipfile
Requires-Python: >=3.8
License-File: LICENSE
Requires-Dist: requests==2.32.3
Requires-Dist: packaging==24.2
Requires-Dist: virtualenv==20.29.3
Requires-Dist: pytest==8.3.5
Dynamic: license-file
